lawaf/__init__.py
lawaf/params.py
lawaf/test.py
lawaf/hamitonian/eigen_modifer.py
lawaf/interfaces/Amn_to_ham.py
lawaf/interfaces/__init__.py
lawaf/interfaces/build_ham.py
lawaf/interfaces/downfolder.py
lawaf/interfaces/select_downfolder.py
lawaf/interfaces/anaddb/__init__.py
lawaf/interfaces/magnon/__init__.py
lawaf/interfaces/magnon/magnon_downfolder.py
lawaf/interfaces/phonopy/__init__.py
lawaf/interfaces/phonopy/ifcwrapper.py
lawaf/interfaces/phonopy/lwf.py
lawaf/interfaces/phonopy/lwf_supercell.py
lawaf/interfaces/phonopy/phonon_downfolder.py
lawaf/interfaces/phonopy/phonon_gui.py
lawaf/interfaces/phonopy/phonopywrapper.py
lawaf/interfaces/siesta/__init__.py
lawaf/interfaces/siesta/siesta_downfolder.py
lawaf/interfaces/wannier90/__init__.py
lawaf/interfaces/wannier90/wannier_downfolder.py
lawaf/io/LWF_json.py
lawaf/io/xsf.py
lawaf/lwf/dipdip.py
lawaf/lwf/gen_atoms.py
lawaf/lwf/lwf.py
lawaf/lwf/lwf_supercell.py
lawaf/mathutils/__init__.py
lawaf/mathutils/align_evecs.py
lawaf/mathutils/evals_freq.py
lawaf/mathutils/geometry.py
lawaf/mathutils/kR_convert.py
lawaf/mathutils/linalg.py
lawaf/mathutils/lowdin.py
lawaf/mathutils/occupation_functions.py
lawaf/mathutils/pert.py
lawaf/plot/__init__.py
lawaf/plot/cif.py
lawaf/plot/mcif.py
lawaf/plot/plot.py
lawaf/plot/testpath.py
lawaf/ui/__init__.py
lawaf/ui/gui.py
lawaf/utils/__init__.py
lawaf/utils/gatherphonopy.py
lawaf/utils/kpoints.py
lawaf/utils/lwf_to_atoms.py
lawaf/utils/nckit.py
lawaf/utils/plotphon.py
lawaf/utils/port.py
lawaf/utils/structurebuilder.py
lawaf/utils/supercell.py
lawaf/utils/symbol.py
lawaf/wannierization/__init__.py
lawaf/wannierization/density_scdmk.py
lawaf/wannierization/dummy.py
lawaf/wannierization/projectedWF.py
lawaf/wannierization/scdmk.py
lawaf/wannierization/semodeWF.py
lawaf/wannierization/wannierizer.py
lawaf/wrapper/__init__.py
lawaf/wrapper/gpawwrapper.py
lawaf/wrapper/ijR.py
lawaf/wrapper/myTB.py
lawaf/wrapper/sislwrapper.py
lawaf/wrapper/utils.py
lawaf/wrapper/w90_parser.py
lawaf-0.2.4.dist-info/licenses/LICENSE
lawaf-0.2.4.dist-info/METADATA
lawaf-0.2.4.dist-info/WHEEL
lawaf-0.2.4.dist-info/top_level.txt
lawaf-0.2.4.dist-info/RECORD
